{
    "preferences": {
        "meeting_time": "set preference for morning time"
    },
    "tasks": [
        {
            "task": "Remind me to call mom Sunday",
            "time": "Detected time"
        },
        {
            "task": "Remind me to call mom Sunday",
            "time": "Detected time"
        },
        {
            "task": "Remind me to call mom Sunday at 7 PM",
            "time": "7 PM"
        },
        {
            "task": "Remind me to call dad Sunday",
            "time": "Sunday"
        },
        {
            "task": "Reminder to attend meetin at 10 pm",
            "time": "10 pm"
        },
        {
            "task": "remind me about the project",
            "time": "No time detected"
        },
        {
            "task": "remind me about the project  ",
            "time": "No time detected"
        },
        {
            "task": "remind me about taxes",
            "time": "No time detected"
        },
        {
            "task": "remind me  to submit undertaking form to kavita mam  on 17 feb 2026",
            "time": "feb 20"
        },
        {
            "task": "REMIND ME TO submit undertaking form to kavita mam on feb 18 2026 ",
            "time": "No time detected"
        },
        {
            "task": "REMIND ME TO submit undertaking form to kavita mam on feb 18 2026  10:00pm",
            "time": "10:00pm"
        },
        {
            "task": "Remind about bill payment with date",
            "time": "No time detected"
        },
        {
            "task": "remind me to submit undertaking form to kavita mam on 17 feb 2026",
            "time": "17 feb 2026"
        },
        {
            "task": "send an email to john sir by 5 pm",
            "time": "5 pm"
        },
        {
            "task": "Send an email to John",
            "time": "No time detected"
        },
        {
            "task": "Submit report to indu mam by 8:45 am",
            "time": "8:45 am"
        },
        {
            "task": "please remind me about the project deadline tomorrow morning",
            "time": "tomorrow"
        },
        {
            "task": "next friday after lunch, remind me to submit the final report to kavita mam",
            "time": "friday"
        }
    ],
    "conversation_history": [
        "I prefer meetings after 10 AM",
        "Remind me to call mom Sunday",
        "Schedule meeting tomorrow",
        "When did I say call mom?",
        "I prefer meetings after 10 AM",
        "Schedule meeting tomorrow",
        "Remind me to call mom Sunday",
        "Remind me to call mom Sunday at 7 PM",
        "When did I mention calling mom?",
        "Remind me to call dad Sunday",
        "Reminder to attend meetin at 10 pm",
        "Submit undertaking form to Kavitha Maam at 10 am",
        "Submit undertaking form to Kavitha Maam at 12 pm",
        "Submit unertaking form to Kavitha maam at 10 am",
        "hello",
        "schedule a meeting tomorrow at 3pm",
        "schedule a meeting tomorrow at 3pm",
        "remind me about the project",
        "create a task to submit the report",
        "set my preference to quiet hours from 9 to 5",
        "what did I say earlier",
        "schedule a meeting tomorrow at 3pm",
        "remind me about the project  ",
        "create a task to submit the report",
        "set my preference to quiet hours",
        "retrieve what I said",
        "schedule meeting tomorrow",
        "remind me about taxes",
        "what have I told you",
        "send an email to alice",
        "set preference for morning time",
        "submit undertaking form to kavita mam",
        "remind me  to submit undertaking form to kavita mam  on 17 feb 2026",
        "REMIND ME TO submit undertaking form to kavita mam on feb 18 2026 ",
        "REMIND ME TO submit undertaking form to kavita mam on feb 18 2026  10:00pm",
        "Remind about bill payment with date",
        "remind me to submit undertaking form to kavita mam on 17 feb 2026",
        "schedule meeting tomorrow with alice",
        "what have I told you about the project",
        "send an email to john sir by 5 pm",
        "set preference for morning time",
        "remind me to submit undertaking form to kavita mam on 17 feb 2026",
        "remind me to submit undertaking form to kavita mam on 17 feb 2026",
        "remind me to submit undertaking form to kavita mam on 17 feb 2026",
        "remind me to submit undertaking form to kavita mam on 17 feb 2026",
        "remind me to submit undertaking form to kavita mam on 17 feb 2026",
        "Send an email to John",
        "Send an email to John",
        "Submit report to indu mam by 8:45 am",
        "Submit report to indu mam by 8:45 am",
        "Submit report to indu mam by 8:45 am",
        "remind me to submit undertaking form to kavita mam on 17 feb 2026",
        "remind me to submit undertaking form to kavita mam on 17 feb 2026",
        "remind me to submit undertaking form to kavita mam on 17 feb 2026",
        "remind me to submit undertaking form to kavita mam on 17 feb 2026",
        "remind me to submit undertaking form to kavita mam on 17 feb 2026",
        "remind me to submit undertaking form to kavita mam on 17 feb 2026",
        "please remind me about the project deadline tomorrow morning",
        "organise a team meeting with alice and bob next monday at 3 pm",
        "next friday after lunch, remind me to submit the final report to kavita mam",
        "please remind me about the project deadline tomorrow morning",
        "please remind me about the project deadline tomorrow morning",
        "remind me to submit undertaking form to kavita mam on 17 feb 2026",
        "remind me to submit undertaking form to kavita mam on 17 feb 2026",
        "remind me to submit undertaking form to kavita mam on 17 feb 2026",
        "remind me to submit undertaking form to kavita mam on 17 feb 2026",
        "remind me to submit undertaking form to kavita mam on 17 feb 2026",
        "remind me to submit undertaking form to kavita mam on 17 feb 2026"
    ]
}